7.Sequence Detector 1011/seq.vhdl
library IEEE;
use IEEE.std_logic_1164.all;

entity sequence is 
    Port(clk : in std_logic; 
    reset : in std_logic; 
    input : in  std_logic;
    output : out std_logic);
end sequence;

architecture behavioral of sequence is 
    type state_type is (s0 , s1 , s2 , s3);
    signal current_state , next_state : state_type;

begin 
    process(clk , reset)
    begin
        if reset = '1' then 
            current_state <= s0;
        elsif rising_edge (clk) then
            current_state <= next_state;
        end if ;
    end process;

    process(current_state , input)
        begin 
            case current_state is
                when s0 =>
                    if input ='1' then
                        output <= '0';
                        next_state <= s1;
                    else 
                        output <='0';
                        next_state <= s0;
                    end if;
                    when s1 =>
                        if input = '0' then
                            output <= '0';
                            next_state <= s2;
                        else
                            next_state <= s1;
                            output <= '0';
                        end if;
                        
                    when s2 =>
                        if input = '1' then
                            output <= '0';
                            next_state <= s3;
                        else
                            output <= '0';
                            next_state <= s0;
                        end if;
                        
                    when s3 =>
                        if input = '1' then
                            output <= '1';
                            next_state <= s3;
                        else
                            output <= '0';
                            next_state <= s2;
                        end if;
                        
                    when others =>
                        next_state <= s0;
                        output <= '0';
                end case;
            end process;
        end behavioral;

7.Sequence Detector 1011/seq_tb.vhdl
library IEEE;
use IEEE.std_logic_1164.all;

entity sequence_tb is
end sequence_tb;

architecture behavioral of sequence_tb is
    -- Constants
    constant CLK_PERIOD : time := 10 ns;

    -- Signals
    signal clk : std_logic := '0';
    signal reset : std_logic := '1'; -- Active low reset
    signal input_sig : std_logic := '0';
    signal output_sig : std_logic;

begin
    dut : entity work.sequence
        port map (
            clk => clk,
            reset => reset,
            input => input_sig,
            output => output_sig
        );

    -- Clock process
    process
    begin
        while now < 100 ns loop  
            clk <= '0';
            wait for CLK_PERIOD / 2;
            clk <= '1';
            wait for CLK_PERIOD / 2;
        end loop;
        wait;
    end process;

    process
    begin
        -- Apply reset
        reset <= '1';  -- Assert reset
        wait for 10 ns;
        reset <= '0';  -- De-assert reset
        wait for 10 ns;

        -- Test sequence: 10011011
        input_sig <= '1'; wait for CLK_PERIOD;
        input_sig <= '0'; wait for CLK_PERIOD;
        input_sig <= '0'; wait for CLK_PERIOD;
        input_sig <= '1'; wait for CLK_PERIOD;
        input_sig <= '1'; wait for CLK_PERIOD;
        input_sig <= '0'; wait for CLK_PERIOD;
        input_sig <= '1'; wait for CLK_PERIOD;
        input_sig <= '1'; wait for CLK_PERIOD;

        wait for 100 ns;

        wait;
    end process;

end behavioral;

7.Sequence Detector 1011/result.vcd
$date
  Sat Feb 10 17:39:59 2024
$end
$version
  GHDL v0
$end
$timescale
  1 fs
$end
$scope module standard $end
$upscope $end
$scope module std_logic_1164 $end
$upscope $end
$scope module sequence_tb $end
$var reg 1 ! clk $end
$var reg 1 " reset $end
$var reg 1 # input_sig $end
$var reg 1 $ output_sig $end
$scope module dut $end
$var reg 1 % clk $end
$var reg 1 & reset $end
$var reg 1 ' input $end
$var reg 1 ( output $end
$comment current_state is not handled $end
$comment next_state is not handled $end
$upscope $end
$upscope $end
$enddefinitions $end
#0
0!
1"
0#
0$
0%
1&
0'
0(
#5000000
1!
1%
#10000000
0!
0"
0%
0&
#15000000
1!
1%
#20000000
0!
1#
0%
1'
#25000000
1!
1%
#30000000
0!
0#
0%
0'
#35000000
1!
1%
#40000000
0!
0%
#45000000
1!
1%
#50000000
0!
1#
0%
1'
#55000000
1!
1%
#60000000
0!
0%
#65000000
1!
1%
#70000000
0!
0#
0%
0'
#75000000
1!
1%
#80000000
0!
1#
0%
1'
#85000000
1!
1$
1%
1(
