1. full_adder/full_adder.vhdl
library IEEE;
use IEEE.std_logic_1164.all;

entity full_adder is
    Port(
        A,B,C : in  std_logic;
        sum,carry : out std_logic
    );
end full_adder;

architecture full_adder1 of full_adder is
    begin 
        sum <= A xor B xor C;
        carry <= (A and B) or (B and C) or (C and A);
    end  full_adder1;

1. full_adder/full_adder_tb.vhdl
library IEEE;
use IEEE.std_logic_1164.all;

entity full_adder_tb is 
end full_adder_tb;

architecture tb of full_adder_tb is 
    component full_adder 
        Port(
            A, B, C: in std_logic;
            sum , carry : out std_logic
        );
    end component;
    
    signal A, B, C, sum, carry : std_logic;

begin
    y1: full_adder port map(
        A => A,
        B => B,
        C => C,
        sum => sum,
        carry => carry
    );

    process 
    begin
        A <= '0'; B <= '0'; C <= '0'; wait for 10 ns;
        A <= '0'; B <= '0'; C <= '1'; wait for 10 ns;
        A <= '0'; B <= '1'; C <= '0'; wait for 10 ns;
        A <= '0'; B <= '1'; C <= '1'; wait for 10 ns;
        A <= '1'; B <= '0'; C <= '0'; wait for 10 ns;
        A <= '1'; B <= '0'; C <= '1'; wait for 10 ns;
        A <= '1'; B <= '1'; C <= '0'; wait for 10 ns;
        A <= '1'; B <= '1'; C <= '1'; wait for 10 ns;
        wait;
    end process;
end tb;

1. full_adder/result.vcd
$date
  Sat Feb 10 11:46:15 2024
$end
$version
  GHDL v0
$end
$timescale
  1 fs
$end
$scope module standard $end
$upscope $end
$scope module std_logic_1164 $end
$upscope $end
$scope module full_adder_tb $end
$var reg 1 ! a $end
$var reg 1 " b $end
$var reg 1 # c $end
$var reg 1 $ sum $end
$var reg 1 % carry $end
$scope module y1 $end
$var reg 1 & a $end
$var reg 1 ' b $end
$var reg 1 ( c $end
$var reg 1 ) sum $end
$var reg 1 * carry $end
$upscope $end
$upscope $end
$enddefinitions $end
#0
0!
0"
0#
0$
0%
0&
0'
0(
0)
0*
#10000000
1#
1$
1(
1)
#20000000
1"
0#
1'
0(
#30000000
1#
0$
1%
1(
0)
1*
#40000000
1!
0"
0#
1$
0%
1&
0'
0(
1)
0*
#50000000
1#
0$
1%
1(
0)
1*
#60000000
1"
0#
1'
0(
#70000000
1#
1$
1(
1)
