2.full adder using the halfadder/full_adder.vhdl
library IEEE;
use IEEE.std_logic_1164.all;

entity halfadder is 
    port (
        A, B: in std_logic;
        Sum, Carry: out std_logic
    );
end halfadder;

architecture ha of halfadder is 
begin
    Sum <= A xor B;
    Carry <= A and B;
end ha;

library IEEE;
use IEEE.std_logic_1164.all;
entity fulladder is 
    port (
        A, B, C: in std_logic;
        Sum, Carry: out std_logic
    );
end fulladder;

architecture ha_fulladder of fulladder is 
    component halfadder is 
        port (
            A, B: in std_logic;
            Sum, Carry: out std_logic
        );
    end component;
    
    signal c1, c2, s1: std_logic;
begin 
    ha1: halfadder port map(A, B, s1, c1);
    ha2: halfadder port map(s1, C, Sum, c2);
    Carry <= c1 or c2;
end ha_fulladder;

2.full adder using the halfadder/full_adder_tb.vhdl
library IEEE;
use IEEE.std_logic_1164.all;

entity full_adder_tb is
end full_adder_tb;

architecture tb_arch of full_adder_tb is
    component fulladder
        Port (
            A, B, C: in std_logic;
            Sum, Carry: out std_logic
        );
    end component;

    signal A_tb, B_tb, C_tb, Sum_tb, Carry_tb: std_logic;

begin
    -- Instantiate the fulladder
    fa: fulladder port map (
        A => A_tb,
        B => B_tb,
        C => C_tb,
        Sum => Sum_tb,
        Carry => Carry_tb
    );

    process
    begin
        -- Test case 1: A=0, B=0, C=0
        A_tb <= '0';
        B_tb <= '0';
        C_tb <= '0';
        wait for 10 ns;
        
        -- Test case 2: A=0, B=0, C=1
        A_tb <= '0';
        B_tb <= '0';
        C_tb <= '1';
        wait for 10 ns;

        -- Test case 3: A=0, B=1, C=0
        A_tb <= '0';
        B_tb <= '1';
        C_tb <= '0';
        wait for 10 ns;
        
        -- Test case 4: A=0, B=1, C=1
        A_tb <= '0';
        B_tb <= '1';
        C_tb <= '1';
        wait for 10 ns;
        
        -- Test case 5: A=1, B=0, C=0
        A_tb <= '1';
        B_tb <= '0';
        C_tb <= '0';
        wait for 10 ns;
        
        -- Test case 6: A=1, B=0, C=1
        A_tb <= '1';
        B_tb <= '0';
        C_tb <= '1';
        wait for 10 ns;
        
        -- Test case 7: A=1, B=1, C=0
        A_tb <= '1';
        B_tb <= '1';
        C_tb <= '0';
        wait for 10 ns;
        
        -- Test case 8: A=1, B=1, C=1
        A_tb <= '1';
        B_tb <= '1';
        C_tb <= '1';
        wait for 10 ns;
        
        -- End of test
        wait;
    end process;

end tb_arch;

2.full adder using the halfadder/result.vcd
$date
  Sat Feb 10 12:23:39 2024
$end
$version
  GHDL v0
$end
$timescale
  1 fs
$end
$scope module standard $end
$upscope $end
$scope module std_logic_1164 $end
$upscope $end
$scope module full_adder_tb $end
$var reg 1 ! a_tb $end
$var reg 1 " b_tb $end
$var reg 1 # c_tb $end
$var reg 1 $ sum_tb $end
$var reg 1 % carry_tb $end
$scope module fa $end
$var reg 1 & a $end
$var reg 1 ' b $end
$var reg 1 ( c $end
$var reg 1 ) sum $end
$var reg 1 * carry $end
$var reg 1 + c1 $end
$var reg 1 , c2 $end
$var reg 1 - s1 $end
$scope module ha1 $end
$var reg 1 . a $end
$var reg 1 / b $end
$var reg 1 0 sum $end
$var reg 1 1 carry $end
$upscope $end
$scope module ha2 $end
$var reg 1 2 a $end
$var reg 1 3 b $end
$var reg 1 4 sum $end
$var reg 1 5 carry $end
$upscope $end
$upscope $end
$upscope $end
$enddefinitions $end
#0
0!
0"
0#
0$
0%
0&
0'
0(
0)
0*
0+
0,
0-
0.
0/
00
01
02
03
04
05
#10000000
1#
1$
1(
1)
13
14
#20000000
1"
0#
1$
1'
0(
1)
1-
1/
10
12
03
14
#30000000
1#
0$
1%
1(
0)
1*
1,
13
04
15
#40000000
1!
0"
0#
1$
0%
1&
0'
0(
1)
0*
0,
1.
0/
03
14
05
#50000000
1#
0$
1%
1(
0)
1*
1,
13
04
15
#60000000
1"
0#
0$
1'
0(
0)
1+
0,
0-
1/
00
11
02
03
04
05
#70000000
1#
1$
1(
1)
13
14
